{"type":"FeatureCollection", "features": [
{"type":"Feature","geometry":{"type":"Point","coordinates":[67.99155062026495,25.06930118180412,0,-1.7976931348623157e+308]},"properties":{"OBJECTID":10,"Name":"FFC","Funded_by":"","Type":"Completed","latitude":25.0693011818,"longitude":67.9915506203}},
{"type":"Feature","geometry":{"type":"Point","coordinates":[67.98659337998055,25.053743566012827,0,-1.7976931348623157e+308]},"properties":{"OBJECTID":11,"Name":"Zorlu","Funded_by":"","Type":"Completed","latitude":25.053743566,"longitude":67.98659338}},
{"type":"Feature","geometry":{"type":"Point","coordinates":[67.9489530273604,25.14644983828947,0,-1.7976931348623157e+308]},"properties":{"OBJECTID":14,"Name":"Lucky","Funded_by":"","Type":"Completed","latitude":25.1464498383,"longitude":67.9489530274}},
{"type":"Feature","geometry":{"type":"Point","coordinates":[67.9330429852456,25.138433657487326,0,-1.7976931348623157e+308]},"properties":{"OBJECTID":15,"Name":"Sachal","Funded_by":"","Type":"Completed","latitude":25.1384336575,"longitude":67.9330429852}},
{"type":"Feature","geometry":{"type":"Point","coordinates":[67.91967473659986,25.117095874075403,0,-1.7976931348623157e+308]},"properties":{"OBJECTID":16,"Name":"TGS","Funded_by":"","Type":"Completed","latitude":25.1170958741,"longitude":67.9196747366}},
{"type":"Feature","geometry":{"type":"Point","coordinates":[67.92463602922942,25.128258300680102,0,-1.7976931348623157e+308]},"properties":{"OBJECTID":17,"Name":"TGT","Funded_by":"","Type":"Completed","latitude":25.1282583007,"longitude":67.9246360292}},
{"type":"Feature","geometry":{"type":"Point","coordinates":[67.94281192672906,25.094794747679487,0,-1.7976931348623157e+308]},"properties":{"OBJECTID":18,"Name":"Sapphire","Funded_by":"","Type":"Completed","latitude":25.0947947477,"longitude":67.9428119267}},
{"type":"Feature","geometry":{"type":"Point","coordinates":[67.94757029992945,25.079332534668765,0,-1.7976931348623157e+308]},"properties":{"OBJECTID":20,"Name":"TGF","Funded_by":"","Type":"Completed","latitude":25.0793325347,"longitude":67.9475702999}},
{"type":"Feature","geometry":{"type":"Point","coordinates":[67.85461632018706,25.10021749773938,0,-1.7976931348623157e+308]},"properties":{"OBJECTID":25,"Name":"UEP Jhimpir","Funded_by":"","Type":"Completed","latitude":25.1002174977,"longitude":67.8546163202}},
{"type":"Feature","geometry":{"type":"Point","coordinates":[68.06571917799772,25.136096755660787,0,-1.7976931348623157e+308]},"properties":{"OBJECTID":35,"Name":"Hawa New","Funded_by":"","Type":"Completed","latitude":25.1360967557,"longitude":68.065719178}},
{"type":"Feature","geometry":{"type":"Point","coordinates":[67.4492567060322,24.603987009792718,0,-1.7976931348623157e+308]},"properties":{"OBJECTID":53,"Name":"Tenaga","Funded_by":"","Type":"Completed","latitude":24.6039870098,"longitude":67.449256706}},
{"type":"Feature","geometry":{"type":"Point","coordinates":[67.49045419300666,24.669180610496824,0,-1.7976931348623157e+308]},"properties":{"OBJECTID":54,"Name":"Dawood-Hydrochina","Funded_by":"","Type":"Completed","latitude":24.6691806105,"longitude":67.490454193}},
{"type":"Feature","geometry":{"type":"Point","coordinates":[67.39993904515086,24.6094495215782,0,-1.7976931348623157e+308]},"properties":{"OBJECTID":56,"Name":"FWEL-I","Funded_by":"","Type":"Completed","latitude":24.6094495216,"longitude":67.3999390452}},
{"type":"Feature","geometry":{"type":"Point","coordinates":[67.4623579918279,24.57344143937098,0,-1.7976931348623157e+308]},"properties":{"OBJECTID":57,"Name":"FWEL-II","Funded_by":"","Type":"Completed","latitude":24.5734414394,"longitude":67.4623579918}},
{"type":"Feature","geometry":{"type":"Point","coordinates":[67.82130455200007,25.06289122600003,0,-1.7976931348623157e+308]},"properties":{"OBJECTID":60,"Name":"TB-B","Funded_by":"","Type":"Completed","latitude":25.062891226,"longitude":67.821304552}},
{"type":"Feature","geometry":{"type":"Point","coordinates":[67.81560722729176,25.048344155158702,0,-1.7976931348623157e+308]},"properties":{"OBJECTID":61,"Name":"TB-A","Funded_by":"","Type":"Completed","latitude":25.0483441552,"longitude":67.8156072273}},
{"type":"Feature","geometry":{"type":"Point","coordinates":[67.83696985300003,25.06684623600006,0,-1.7976931348623157e+308]},"properties":{"OBJECTID":62,"Name":"TB-C","Funded_by":"","Type":"Completed","latitude":25.066846236,"longitude":67.836969853}},
{"type":"Feature","geometry":{"type":"Point","coordinates":[67.4654643491005,24.70838209535748,0,-1.7976931348623157e+308]},"properties":{"OBJECTID":63,"Name":"Zephyr","Funded_by":"","Type":"Completed","latitude":24.7083820954,"longitude":67.4654643491}}
]}